{
  "rank": 15,
  "candidate_id": "c0864ac279052a8c",
  "filter_preset": "self_limit",
  "metrics": {
    "candidate_id": "c0864ac279052a8c",
    "filter_preset": "self_limit",
    "passes_recommendation_gate": false,
    "passes_dd": false,
    "passes_edge": true,
    "passes_consistency": true,
    "passes_oos": true,
    "score": 3420.1574305556,
    "fixed_no_bonus_profit": 3613.8125000000146,
    "fixed_with_bonus_profit": 3791.142499999987,
    "bonus_contribution": 177.32999999997264,
    "concurrent_risk_max_dd_pct": 95.72753755638118,
    "risk_net_profit_with_bonus": 127593934363.7804,
    "stable_months": 14,
    "total_months": 18,
    "stable_fraction": 0.7777777777777778,
    "worst_month_pnl": -164.82249999999067,
    "oos_fixed_no_bonus_profit": 2437.657500000132
  },
  "monthly": [
    {
      "month": "2025-01",
      "signals": 399,
      "wins": 149,
      "losses": 122,
      "no_fills": 126,
      "open": 0,
      "pnl": 126.78749999999582,
      "trading_pnl": 126.78749999999582,
      "bonus": 0.0,
      "closed_lots": 2.7299999999999858,
      "equity_start": 1000.0,
      "equity_end": 1126.7874999999958,
      "win_rate_pct": 54.981549815498155,
      "pnl_pct": 12.67874999999958
    },
    {
      "month": "2025-02",
      "signals": 365,
      "wins": 171,
      "losses": 118,
      "no_fills": 73,
      "open": 0,
      "pnl": 76.97999999997364,
      "trading_pnl": 76.97999999997364,
      "bonus": 0.0,
      "closed_lots": 2.9199999999999817,
      "equity_start": 1126.7874999999958,
      "equity_end": 1203.7674999999695,
      "win_rate_pct": 59.16955017301038,
      "pnl_pct": 6.8318116769997825
    },
    {
      "month": "2025-03",
      "signals": 384,
      "wins": 155,
      "losses": 155,
      "no_fills": 74,
      "open": 0,
      "pnl": -164.82249999999067,
      "trading_pnl": -164.82249999999067,
      "bonus": 0.0,
      "closed_lots": 3.099999999999978,
      "equity_start": 1203.7674999999695,
      "equity_end": 1038.9449999999788,
      "win_rate_pct": 50.0,
      "pnl_pct": -13.69222046616102
    },
    {
      "month": "2025-04",
      "signals": 382,
      "wins": 201,
      "losses": 136,
      "no_fills": 41,
      "open": 0,
      "pnl": 332.8074999999917,
      "trading_pnl": 332.8074999999917,
      "bonus": 0.0,
      "closed_lots": 3.4099999999999713,
      "equity_start": 1038.9449999999788,
      "equity_end": 1373.8424999999702,
      "win_rate_pct": 59.64391691394659,
      "pnl_pct": 32.03321638777784
    },
    {
      "month": "2025-05",
      "signals": 388,
      "wins": 192,
      "losses": 145,
      "no_fills": 49,
      "open": 0,
      "pnl": -41.759999999995216,
      "trading_pnl": -41.759999999995216,
      "bonus": 0.0,
      "closed_lots": 3.3899999999999717,
      "equity_start": 1371.7524999999705,
      "equity_end": 1329.9924999999753,
      "win_rate_pct": 56.97329376854599,
      "pnl_pct": -3.0442809471822443
    },
    {
      "month": "2025-06",
      "signals": 372,
      "wins": 175,
      "losses": 137,
      "no_fills": 58,
      "open": 0,
      "pnl": -0.2200000000084401,
      "trading_pnl": -0.2200000000084401,
      "bonus": 0.0,
      "closed_lots": 3.139999999999977,
      "equity_start": 1329.9924999999753,
      "equity_end": 1329.7724999999668,
      "win_rate_pct": 56.08974358974359,
      "pnl_pct": -0.016541446662928116
    },
    {
      "month": "2025-07",
      "signals": 421,
      "wins": 188,
      "losses": 149,
      "no_fills": 83,
      "open": 0,
      "pnl": 67.65999999999349,
      "trading_pnl": 67.65999999999349,
      "bonus": 0.0,
      "closed_lots": 3.379999999999972,
      "equity_start": 1329.7724999999668,
      "equity_end": 1397.4324999999603,
      "win_rate_pct": 55.78635014836796,
      "pnl_pct": 5.088088376018844
    },
    {
      "month": "2025-08",
      "signals": 388,
      "wins": 161,
      "losses": 152,
      "no_fills": 74,
      "open": 0,
      "pnl": -79.64500000002636,
      "trading_pnl": -79.64500000002636,
      "bonus": 0.0,
      "closed_lots": 3.139999999999977,
      "equity_start": 1397.4324999999603,
      "equity_end": 1317.787499999934,
      "win_rate_pct": 51.43769968051119,
      "pnl_pct": -5.699380828771953
    },
    {
      "month": "2025-09",
      "signals": 402,
      "wins": 198,
      "losses": 138,
      "no_fills": 62,
      "open": 0,
      "pnl": 41.66499999996904,
      "trading_pnl": 41.66499999996904,
      "bonus": 0.0,
      "closed_lots": 3.3999999999999715,
      "equity_start": 1317.787499999934,
      "equity_end": 1359.452499999903,
      "win_rate_pct": 58.92857142857143,
      "pnl_pct": 3.161738899478947
    },
    {
      "month": "2025-10",
      "signals": 424,
      "wins": 249,
      "losses": 123,
      "no_fills": 45,
      "open": 0,
      "pnl": 498.8349999999705,
      "trading_pnl": 498.8349999999705,
      "bonus": 0.0,
      "closed_lots": 3.789999999999963,
      "equity_start": 1359.452499999903,
      "equity_end": 1858.2874999998735,
      "win_rate_pct": 66.93548387096774,
      "pnl_pct": 36.69381607669309
    },
    {
      "month": "2025-11",
      "signals": 366,
      "wins": 215,
      "losses": 119,
      "no_fills": 30,
      "open": 0,
      "pnl": 253.27249999998548,
      "trading_pnl": 253.27249999998548,
      "bonus": 0.0,
      "closed_lots": 3.3599999999999723,
      "equity_start": 1858.2874999998735,
      "equity_end": 2111.559999999859,
      "win_rate_pct": 64.37125748502994,
      "pnl_pct": 13.62934960279304
    },
    {
      "month": "2025-12",
      "signals": 402,
      "wins": 224,
      "losses": 145,
      "no_fills": 31,
      "open": 0,
      "pnl": 64.59500000002481,
      "trading_pnl": 64.59500000002481,
      "bonus": 0.0,
      "closed_lots": 3.709999999999965,
      "equity_start": 2111.559999999859,
      "equity_end": 2176.154999999884,
      "win_rate_pct": 60.70460704607046,
      "pnl_pct": 3.0591126939338276
    },
    {
      "month": "2026-01",
      "signals": 397,
      "wins": 234,
      "losses": 113,
      "no_fills": 36,
      "open": 0,
      "pnl": 581.3949999999886,
      "trading_pnl": 581.3949999999886,
      "bonus": 0.0,
      "closed_lots": 3.609999999999967,
      "equity_start": 2176.154999999884,
      "equity_end": 2757.5499999998724,
      "win_rate_pct": 67.43515850144092,
      "pnl_pct": 26.716617152731292
    },
    {
      "month": "2026-02",
      "signals": 362,
      "wins": 226,
      "losses": 99,
      "no_fills": 19,
      "open": 0,
      "pnl": 691.3325000000095,
      "trading_pnl": 691.3325000000095,
      "bonus": 0.0,
      "closed_lots": 3.429999999999971,
      "equity_start": 2757.5499999998724,
      "equity_end": 3448.882499999882,
      "win_rate_pct": 69.53846153846153,
      "pnl_pct": 25.070533625865043
    },
    {
      "month": "2026-03",
      "signals": 401,
      "wins": 257,
      "losses": 101,
      "no_fills": 22,
      "open": 0,
      "pnl": 682.6175000000285,
      "trading_pnl": 682.6175000000285,
      "bonus": 0.0,
      "closed_lots": 3.789999999999963,
      "equity_start": 3448.882499999882,
      "equity_end": 4131.49999999991,
      "win_rate_pct": 71.7877094972067,
      "pnl_pct": 19.79242551754233
    },
    {
      "month": "2026-04",
      "signals": 377,
      "wins": 214,
      "losses": 136,
      "no_fills": 20,
      "open": 0,
      "pnl": 118.75000000004366,
      "trading_pnl": 118.75000000004366,
      "bonus": 0.0,
      "closed_lots": 3.569999999999968,
      "equity_start": 4131.49999999991,
      "equity_end": 4250.249999999954,
      "win_rate_pct": 61.142857142857146,
      "pnl_pct": 2.8742587437987717
    },
    {
      "month": "2026-05",
      "signals": 387,
      "wins": 220,
      "losses": 131,
      "no_fills": 28,
      "open": 0,
      "pnl": 220.157500000043,
      "trading_pnl": 220.157500000043,
      "bonus": 0.0,
      "closed_lots": 3.5899999999999674,
      "equity_start": 4250.249999999954,
      "equity_end": 4470.407499999997,
      "win_rate_pct": 62.67806267806267,
      "pnl_pct": 5.17987177224976
    },
    {
      "month": "2026-06",
      "signals": 179,
      "wins": 106,
      "losses": 49,
      "no_fills": 13,
      "open": 1,
      "pnl": 143.40500000001884,
      "trading_pnl": 143.40500000001884,
      "bonus": 0.0,
      "closed_lots": 1.6500000000000012,
      "equity_start": 4470.407499999997,
      "equity_end": 4613.812500000015,
      "win_rate_pct": 68.38709677419355,
      "pnl_pct": 3.2078731077652085
    }
  ],
  "config": {
    "initial_capital": 1000.0,
    "sizing_mode": "risk",
    "lot_per_entry": 0.5,
    "risk_per_signal": 0.05,
    "minimum_lot": 0.01,
    "lot_step": 0.01,
    "bonus_per_closed_lot": 3.0,
    "entry_count": 1,
    "entry_ladder": "signal_range_3",
    "entry_sl_gap": 2.0,
    "activation_delay_minutes": 1,
    "pending_expiry_minutes": 300,
    "max_hold_minutes": 120,
    "sl_multiplier": 1.3,
    "final_target": "TP3",
    "lock_after_tp1": true,
    "lock_after_tp2": true,
    "shared_sl": false,
    "per_entry_targets": [],
    "bep_after_move": 0.0,
    "runner_trail_from": "TP3",
    "scale_out_at_tp1": false,
    "scale_out_at_tp2": false,
    "bep_after_tp1": false,
    "bep_buffer": 0.0,
    "trailing_close_after_stage": 0,
    "runner_no_final_cap": false,
    "trailing_open_distance": 1.0,
    "trailing_close_distance": 5.0,
    "trailing_close_min_step": 0.0,
    "trend_runner_enabled": false,
    "trend_runner_ema_fast": 21,
    "trend_runner_ema_slow": 55,
    "trend_runner_atr_period": 14,
    "trend_runner_atr_multiplier": 3.0,
    "trend_runner_override_max_hold": true,
    "tp1_lock_delay_minutes": 10,
    "tp2_lock_delay_minutes": 10,
    "profit_lock_mode": "bep_plus_half_tp1",
    "bep_trigger_distance": 6.0,
    "tp1_lock_fraction": 0.75,
    "tp2_lock_target": "TP2",
    "runner_after_tp3": false,
    "tp3_lock_target": "TP2"
  },
  "live_command": "python tools/auto_explicit.py \\\n  --signals generated/live_provider_self_limit.txt \\\n  --positions-json positions.json \\\n  --watch-interval 5 \\\n  --mt5-symbol XAUUSD \\\n  --mt5-server-offset 3 \\\n  --mt5-history-bars 3000 \\\n  --initial-capital 1000.0 \\\n  --sizing-mode risk \\\n  --lot 0.5 \\\n  --risk 0.05 \\\n  --minimum-lot 0.01 \\\n  --lot-step 0.01 \\\n  --bonus-per-closed-lot 3.0 \\\n  --entries 1 \\\n  --entry-ladder signal_range_3 \\\n  --entry-sl-gap 2.0 \\\n  --activation-delay 1 \\\n  --pending-expiry 300 \\\n  --max-hold 120 \\\n  --sl-multiplier 1.3 \\\n  --final-target TP3 \\\n  --lock-after-tp1 true \\\n  --lock-after-tp2 true \\\n  --tp1-lock-delay-minutes 10 \\\n  --tp2-lock-delay-minutes 10 \\\n  --profit-lock-mode bep_plus_half_tp1 \\\n  --bep-trigger-distance 6.0 \\\n  --tp1-lock-fraction 0.75 \\\n  --tp2-lock-target TP2 \\\n  --runner-after-tp3 false \\\n  --tp3-lock-target TP2 \\\n  --trailing-open-distance 1.0 \\\n  --trailing-close-distance 5.0"
}