{
  "rank": 7,
  "candidate_id": "b4a4ef09328afcc0",
  "filter_preset": "self_limit",
  "metrics": {
    "bonus_contribution": 23.669999999978472,
    "candidate_id": "b4a4ef09328afcc0",
    "concurrent_risk_max_dd_pct": 38.61900000000103,
    "filter_preset": "self_limit",
    "fixed_no_bonus_profit": 747.9469999999815,
    "fixed_with_bonus_profit": 771.61699999996,
    "oos_fixed_no_bonus_profit": 464.80999999999676,
    "passes_consistency": true,
    "passes_dd": true,
    "passes_edge": true,
    "passes_oos": true,
    "passes_recommendation_gate": true,
    "risk_net_profit_with_bonus": 1717.8554999999387,
    "score": 739.4916666666504,
    "stable_fraction": 0.8333333333333334,
    "stable_months": 15,
    "total_months": 18,
    "worst_month_pnl": -36.61050000000114
  },
  "monthly": [
    {
      "month": "2025-01",
      "signals": 57,
      "wins": 11,
      "losses": 16,
      "no_fills": 30,
      "open": 0,
      "pnl": -36.61050000000114,
      "trading_pnl": -36.61050000000114,
      "bonus": 0.0,
      "closed_lots": 0.4300000000000001,
      "equity_start": 1000.0,
      "equity_end": 963.3894999999989,
      "win_rate_pct": 40.74074074074074,
      "pnl_pct": -3.661050000000114
    },
    {
      "month": "2025-02",
      "signals": 42,
      "wins": 11,
      "losses": 10,
      "no_fills": 20,
      "open": 0,
      "pnl": -25.985000000000582,
      "trading_pnl": -25.985000000000582,
      "bonus": 0.0,
      "closed_lots": 0.33000000000000007,
      "equity_start": 963.3894999999989,
      "equity_end": 937.4044999999983,
      "win_rate_pct": 52.38095238095239,
      "pnl_pct": -2.6972475826237066
    },
    {
      "month": "2025-03",
      "signals": 50,
      "wins": 17,
      "losses": 14,
      "no_fills": 17,
      "open": 0,
      "pnl": 20.46100000000206,
      "trading_pnl": 20.46100000000206,
      "bonus": 0.0,
      "closed_lots": 0.4900000000000002,
      "equity_start": 937.4044999999983,
      "equity_end": 957.8655000000003,
      "win_rate_pct": 54.83870967741935,
      "pnl_pct": 2.1827290139957825
    },
    {
      "month": "2025-04",
      "signals": 48,
      "wins": 13,
      "losses": 10,
      "no_fills": 19,
      "open": 0,
      "pnl": 70.96349999999939,
      "trading_pnl": 70.96349999999939,
      "bonus": 0.0,
      "closed_lots": 0.41000000000000014,
      "equity_start": 957.8655000000003,
      "equity_end": 1028.8289999999997,
      "win_rate_pct": 56.52173913043478,
      "pnl_pct": 7.408503594711299
    },
    {
      "month": "2025-05",
      "signals": 55,
      "wins": 10,
      "losses": 12,
      "no_fills": 27,
      "open": 0,
      "pnl": 3.2030000000031578,
      "trading_pnl": 3.2030000000031578,
      "bonus": 0.0,
      "closed_lots": 0.42000000000000015,
      "equity_start": 1028.8289999999997,
      "equity_end": 1032.0320000000029,
      "win_rate_pct": 45.45454545454545,
      "pnl_pct": 0.3113248168551974
    },
    {
      "month": "2025-06",
      "signals": 57,
      "wins": 17,
      "losses": 16,
      "no_fills": 22,
      "open": 0,
      "pnl": -21.461500000000342,
      "trading_pnl": -21.461500000000342,
      "bonus": 0.0,
      "closed_lots": 0.5500000000000002,
      "equity_start": 1032.0320000000029,
      "equity_end": 1010.5705000000025,
      "win_rate_pct": 51.515151515151516,
      "pnl_pct": -2.0795382313726978
    },
    {
      "month": "2025-07",
      "signals": 55,
      "wins": 14,
      "losses": 10,
      "no_fills": 30,
      "open": 0,
      "pnl": 17.305999999998676,
      "trading_pnl": 17.305999999998676,
      "bonus": 0.0,
      "closed_lots": 0.3700000000000001,
      "equity_start": 1010.5705000000025,
      "equity_end": 1027.8765000000012,
      "win_rate_pct": 58.333333333333336,
      "pnl_pct": 1.7124980394736076
    },
    {
      "month": "2025-08",
      "signals": 52,
      "wins": 18,
      "losses": 10,
      "no_fills": 21,
      "open": 0,
      "pnl": 31.6074999999978,
      "trading_pnl": 31.6074999999978,
      "bonus": 0.0,
      "closed_lots": 0.4100000000000002,
      "equity_start": 1027.8765000000012,
      "equity_end": 1059.483999999999,
      "win_rate_pct": 64.28571428571429,
      "pnl_pct": 3.075028955326614
    },
    {
      "month": "2025-09",
      "signals": 45,
      "wins": 15,
      "losses": 12,
      "no_fills": 15,
      "open": 0,
      "pnl": 114.21399999999723,
      "trading_pnl": 114.21399999999723,
      "bonus": 0.0,
      "closed_lots": 0.44000000000000017,
      "equity_start": 1059.483999999999,
      "equity_end": 1173.6979999999962,
      "win_rate_pct": 55.55555555555556,
      "pnl_pct": 10.780153357671974
    },
    {
      "month": "2025-10",
      "signals": 51,
      "wins": 11,
      "losses": 11,
      "no_fills": 23,
      "open": 0,
      "pnl": 7.756499999996326,
      "trading_pnl": 7.756499999996326,
      "bonus": 0.0,
      "closed_lots": 0.44000000000000017,
      "equity_start": 1173.6979999999962,
      "equity_end": 1181.4544999999925,
      "win_rate_pct": 50.0,
      "pnl_pct": 0.6608599486406512
    },
    {
      "month": "2025-11",
      "signals": 52,
      "wins": 20,
      "losses": 6,
      "no_fills": 20,
      "open": 0,
      "pnl": 63.751999999997224,
      "trading_pnl": 63.751999999997224,
      "bonus": 0.0,
      "closed_lots": 0.4600000000000002,
      "equity_start": 1181.4544999999925,
      "equity_end": 1245.2064999999898,
      "win_rate_pct": 76.92307692307693,
      "pnl_pct": 5.3960605338587
    },
    {
      "month": "2025-12",
      "signals": 62,
      "wins": 22,
      "losses": 11,
      "no_fills": 23,
      "open": 0,
      "pnl": 37.930499999994936,
      "trading_pnl": 37.930499999994936,
      "bonus": 0.0,
      "closed_lots": 0.5700000000000003,
      "equity_start": 1245.2064999999898,
      "equity_end": 1283.1369999999847,
      "win_rate_pct": 66.66666666666666,
      "pnl_pct": 3.0461212658298242
    },
    {
      "month": "2026-01",
      "signals": 45,
      "wins": 17,
      "losses": 9,
      "no_fills": 16,
      "open": 0,
      "pnl": 17.84950000000208,
      "trading_pnl": 17.84950000000208,
      "bonus": 0.0,
      "closed_lots": 0.4200000000000002,
      "equity_start": 1283.1369999999847,
      "equity_end": 1300.9864999999868,
      "win_rate_pct": 65.38461538461539,
      "pnl_pct": 1.391082947495263
    },
    {
      "month": "2026-02",
      "signals": 53,
      "wins": 14,
      "losses": 5,
      "no_fills": 24,
      "open": 0,
      "pnl": 64.32099999999991,
      "trading_pnl": 64.32099999999991,
      "bonus": 0.0,
      "closed_lots": 0.4100000000000002,
      "equity_start": 1300.9864999999868,
      "equity_end": 1365.3074999999867,
      "win_rate_pct": 73.68421052631578,
      "pnl_pct": 4.94401748211842
    },
    {
      "month": "2026-03",
      "signals": 64,
      "wins": 26,
      "losses": 8,
      "no_fills": 22,
      "open": 0,
      "pnl": 204.88799999999992,
      "trading_pnl": 204.88799999999992,
      "bonus": 0.0,
      "closed_lots": 0.5800000000000003,
      "equity_start": 1365.3074999999867,
      "equity_end": 1570.1954999999866,
      "win_rate_pct": 76.47058823529412,
      "pnl_pct": 15.006729253300222
    },
    {
      "month": "2026-04",
      "signals": 55,
      "wins": 16,
      "losses": 7,
      "no_fills": 23,
      "open": 0,
      "pnl": 80.22049999999854,
      "trading_pnl": 80.22049999999854,
      "bonus": 0.0,
      "closed_lots": 0.4500000000000002,
      "equity_start": 1570.1954999999866,
      "equity_end": 1650.4159999999852,
      "win_rate_pct": 69.56521739130434,
      "pnl_pct": 5.108949809116076
    },
    {
      "month": "2026-05",
      "signals": 54,
      "wins": 17,
      "losses": 9,
      "no_fills": 21,
      "open": 0,
      "pnl": 49.50549999999748,
      "trading_pnl": 49.50549999999748,
      "bonus": 0.0,
      "closed_lots": 0.47000000000000014,
      "equity_start": 1650.4159999999852,
      "equity_end": 1699.9214999999826,
      "win_rate_pct": 65.38461538461539,
      "pnl_pct": 2.9995770763248735
    },
    {
      "month": "2026-06",
      "signals": 26,
      "wins": 8,
      "losses": 6,
      "no_fills": 10,
      "open": 1,
      "pnl": 48.02549999999883,
      "trading_pnl": 48.02549999999883,
      "bonus": 0.0,
      "closed_lots": 0.24,
      "equity_start": 1699.9214999999826,
      "equity_end": 1747.9469999999815,
      "win_rate_pct": 57.14285714285714,
      "pnl_pct": 2.8251598676762026
    }
  ],
  "config": {
    "activation_delay_minutes": 0,
    "bep_after_move": 0.0,
    "bep_after_tp1": false,
    "bep_buffer": 0.0,
    "bep_trigger_distance": 4.0,
    "bonus_per_closed_lot": 3.0,
    "entry_count": 2,
    "entry_ladder": "range_to_sl",
    "entry_sl_gap": 0.0,
    "final_target": "TP3",
    "initial_capital": 1000.0,
    "lock_after_tp1": false,
    "lock_after_tp2": true,
    "lot_per_entry": 0.5,
    "lot_step": 0.01,
    "max_hold_minutes": 90,
    "minimum_lot": 0.01,
    "pending_expiry_minutes": 420,
    "per_entry_targets": [],
    "profit_lock_mode": "bep_plus_half_tp1",
    "risk_per_signal": 0.05,
    "runner_after_tp3": false,
    "runner_no_final_cap": false,
    "runner_trail_from": "TP3",
    "scale_out_at_tp1": false,
    "scale_out_at_tp2": false,
    "shared_sl": true,
    "sizing_mode": "risk",
    "sl_multiplier": 1.15,
    "tp1_lock_delay_minutes": 0,
    "tp1_lock_fraction": 0.5,
    "tp2_lock_delay_minutes": 5,
    "tp2_lock_target": "TP1",
    "tp3_lock_target": "TP2",
    "trailing_close_after_stage": 0,
    "trailing_close_distance": 8.0,
    "trailing_close_min_step": 0.0,
    "trailing_open_distance": 1.0,
    "trend_runner_atr_multiplier": 3.0,
    "trend_runner_atr_period": 14,
    "trend_runner_ema_fast": 21,
    "trend_runner_ema_slow": 55,
    "trend_runner_enabled": false,
    "trend_runner_override_max_hold": true
  },
  "live_command": "python tools/auto_explicit.py \\\n  --signals generated/live_provider_self_limit.txt \\\n  --positions-json positions.json \\\n  --watch-interval 5 \\\n  --mt5-symbol XAUUSD \\\n  --mt5-server-offset 3 \\\n  --mt5-history-bars 3000 \\\n  --initial-capital 1000.0 \\\n  --sizing-mode risk \\\n  --lot 0.5 \\\n  --risk 0.05 \\\n  --minimum-lot 0.01 \\\n  --lot-step 0.01 \\\n  --bonus-per-closed-lot 3.0 \\\n  --entries 2 \\\n  --entry-ladder range_to_sl \\\n  --entry-sl-gap 0.0 \\\n  --activation-delay 0 \\\n  --pending-expiry 420 \\\n  --max-hold 90 \\\n  --sl-multiplier 1.15 \\\n  --final-target TP3 \\\n  --lock-after-tp1 false \\\n  --lock-after-tp2 true \\\n  --tp1-lock-delay-minutes 0 \\\n  --tp2-lock-delay-minutes 5 \\\n  --profit-lock-mode bep_plus_half_tp1 \\\n  --bep-trigger-distance 4.0 \\\n  --tp1-lock-fraction 0.5 \\\n  --tp2-lock-target TP1 \\\n  --runner-after-tp3 false \\\n  --tp3-lock-target TP2 \\\n  --trailing-open-distance 1.0 \\\n  --trailing-close-distance 8.0"
}